Workbook

Sheet Calculator
A1: Virginia Ch. 15 Excess Interest Refund Calculator
A2: Yellow cells with blue text are inputs. Enter each payment on the Ledger sheet. Everything else calculates.
A3: INPUTS
A4: Loan amount | B4: 50000
A5: Contract APR | B5: 0.24
A6: Lawful rate | B6: 0.12
A7: Day-count basis (365 or 360) | B7: 365
A8: Loan date | B8: 45672
A10: CHECK
A11: Over the $35,000 Ch. 15 limit? | B11: =IF(B4>35000,"Yes - 12% limit applies","No - licensee may charge up to 36%") -> Yes - 12% limit applies
A13: RESULTS
A14: Payments entered | B14: =COUNT(Ledger!B7:B406) -> 3
A15: Total paid | B15: =SUM(Ledger!G7:G406) -> 4315.08
A16: Interest paid (charged) | B16: =SUM(Ledger!H7:H406) -> 2931.9285
A17: Interest allowed at 12% | B17: =SUM(Ledger!I7:I406) -> 1465.965
A18: Excess interest | B18: =SUM(Ledger!J7:J406) -> 1465.9635
A19: Unauthorized fees paid | B19: =SUM(Ledger!M7:M406) -> 0
A20: Refund - 6.2-1542(A) | B20: =B18+B19 -> 1465.9635
A21: Penalty (2x) - 6.2-1542(B) | B21: =2*B20 -> 2931.927
A22: TOTAL OWED TO BORROWER (licensed lender) | B22: =B20+B21 -> 4397.8905
A24: Current principal balance | B24: =IF(B14=0,B4,INDEX(Ledger!L6:L406,B14+1)) -> 48616.848
A25: If lender is UNLICENSED - 6.2-1541: all payments recoverable | B25: =B15 -> 4315.08
A26: If lender is UNLICENSED - balance lender cannot collect | B26: =B24 -> 48616.848
A28: NOTES
A29: 1. Excess is figured payment by payment: interest charged minus interest at 12% on the same prior balance for the same number of days.
A30: Periods where interest charged was at or below 12% count as zero excess (no offset).
A31: 2. If your statement shows interest and/or principal split out, enter them in the Ledger - they override the calculated figures.
A32: 3. Penalty does not apply to a bona fide one-time computation error (6.2-1542(B)); the refund still does.
A33: 4. The 12% comparison uses the lender's actual balances. Recomputing the whole loan at 12% from day one would give a somewhat larger refund.
A34: 5. Statutes: Va. Code 6.2-1520, 6.2-1541, 6.2-1542 - https://law.lis.virginia.gov/vacodefull/title6.2/chapter15/
A35: 6. Not legal advice - have an attorney confirm before relying on these totals.

Sheet Ledger
A1: Payment Ledger
A2: Enter payments in date order, no blank rows. Fill in Date plus EITHER Total payment OR the statement split (Principal and/or Interest).
A3: Rows 7-9 are EXAMPLES - overwrite them with your transaction history. Optional columns can be left blank.
A4: INPUT columns: B, C, D, E, M | F4: CALCULATED columns: F - L
A5: # | B5: Payment date | C5: Total payment | D5: Principal paid (statement, optional) | E5: Interest paid (statement, optional) | F5: Days since prior payment | G5: Payment used | H5: Interest charged | I5: Interest at 12% | J5: Excess interest | K5: Principal applied | L5: Principal balance | M5: Unauthorized fees paid (optional)
A6: Start | B6: =Calculator!B8 -> 45672 | L6: =Calculator!B4 -> 50000
A7: 1 | B7: 45703 | C7: 1438.36 | F7: =IF($B7="","",$B7-$B6) -> 31 | G7: =IF($B7="","",IF($C7<>"",$C7,N($D7)+N($E7))) -> 1438.36 | H7: =IF($B7="","",IF($E7<>"",$E7,$L6*Calculator!$B$5*$F7/Calculator!$B$7)) -> 1019.1781 | I7: =IF($B7="","",$L6*Calculator!$B$6*$F7/Calculator!$B$7) -> 509.58904 | J7: =IF($B7="","",MAX(0,$H7-$I7)) -> 509.58904 | K7: =IF($B7="","",IF($D7<>"",$D7,$G7-$H7)) -> 419.18192 | L7: =IF($B7="","",$L6-$K7) -> 49580.818
A8: 2 | B8: 45731 | C8: 1438.36 | F8: =IF($B8="","",$B8-$B7) -> 28 | G8: =IF($B8="","",IF($C8<>"",$C8,N($D8)+N($E8))) -> 1438.36 | H8: =IF($B8="","",IF($E8<>"",$E8,$L7*Calculator!$B$5*$F8/Calculator!$B$7)) -> 912.8304 | I8: =IF($B8="","",$L7*Calculator!$B$6*$F8/Calculator!$B$7) -> 456.4152 | J8: =IF($B8="","",MAX(0,$H8-$I8)) -> 456.4152 | K8: =IF($B8="","",IF($D8<>"",$D8,$G8-$H8)) -> 525.5296 | L8: =IF($B8="","",$L7-$K8) -> 49055.288
A9: 3 | B9: 45762 | D9: 438.44 | E9: 999.92 | F9: =IF($B9="","",$B9-$B8) -> 31 | G9: =IF($B9="","",IF($C9<>"",$C9,N($D9)+N($E9))) -> 1438.36 | H9: =IF($B9="","",IF($E9<>"",$E9,$L8*Calculator!$B$5*$F9/Calculator!$B$7)) -> 999.92 | I9: =IF($B9="","",$L8*Calculator!$B$6*$F9/Calculator!$B$7) -> 499.96075 | J9: =IF($B9="","",MAX(0,$H9-$I9)) -> 499.95925 | K9: =IF($B9="","",IF($D9<>"",$D9,$G9-$H9)) -> 438.44 | L9: =IF($B9="","",$L8-$K9) -> 48616.848
A10: 4 | F10: =IF($B10="","",$B10-$B9) | G10: =IF($B10="","",IF($C10<>"",$C10,N($D10)+N($E10))) | H10: =IF($B10="","",IF($E10<>"",$E10,$L9*Calculator!$B$5*$F10/Calculator!$B$7)) | I10: =IF($B10="","",$L9*Calculator!$B$6*$F10/Calculator!$B$7) | J10: =IF($B10="","",MAX(0,$H10-$I10)) | K10: =IF($B10="","",IF($D10<>"",$D10,$G10-$H10)) | L10: =IF($B10="","",$L9-$K10)
A11: 5 | F11: =IF($B11="","",$B11-$B10) | G11: =IF($B11="","",IF($C11<>"",$C11,N($D11)+N($E11))) | H11: =IF($B11="","",IF($E11<>"",$E11,$L10*Calculator!$B$5*$F11/Calculator!$B$7)) | I11: =IF($B11="","",$L10*Calculator!$B$6*$F11/Calculator!$B$7) | J11: =IF($B11="","",MAX(0,$H11-$I11)) | K11: =IF($B11="","",IF($D11<>"",$D11,$G11-$H11)) | L11: =IF($B11="","",$L10-$K11)
A12: 6 | F12: =IF($B12="","",$B12-$B11) | G12: =IF($B12="","",IF($C12<>"",$C12,N($D12)+N($E12))) | H12: =IF($B12="","",IF($E12<>"",$E12,$L11*Calculator!$B$5*$F12/Calculator!$B$7)) | I12: =IF($B12="","",$L11*Calculator!$B$6*$F12/Calculator!$B$7) | J12: =IF($B12="","",MAX(0,$H12-$I12)) | K12: =IF($B12="","",IF($D12<>"",$D12,$G12-$H12)) | L12: =IF($B12="","",$L11-$K12)
A13: 7 | F13: =IF($B13="","",$B13-$B12) | G13: =IF($B13="","",IF($C13<>"",$C13,N($D13)+N($E13))) | H13: =IF($B13="","",IF($E13<>"",$E13,$L12*Calculator!$B$5*$F13/Calculator!$B$7)) | I13: =IF($B13="","",$L12*Calculator!$B$6*$F13/Calculator!$B$7) | J13: =IF($B13="","",MAX(0,$H13-$I13)) | K13: =IF($B13="","",IF($D13<>"",$D13,$G13-$H13)) | L13: =IF($B13="","",$L12-$K13)
A14: 8 | F14: =IF($B14="","",$B14-$B13) | G14: =IF($B14="","",IF($C14<>"",$C14,N($D14)+N($E14))) | H14: =IF($B14="","",IF($E14<>"",$E14,$L13*Calculator!$B$5*$F14/Calculator!$B$7)) | I14: =IF($B14="","",$L13*Calculator!$B$6*$F14/Calculator!$B$7) | J14: =IF($B14="","",MAX(0,$H14-$I14)) | K14: =IF($B14="","",IF($D14<>"",$D14,$G14-$H14)) | L14: =IF($B14="","",$L13-$K14)
A15: 9 | F15: =IF($B15="","",$B15-$B14) | G15: =IF($B15="","",IF($C15<>"",$C15,N($D15)+N($E15))) | H15: =IF($B15="","",IF($E15<>"",$E15,$L14*Calculator!$B$5*$F15/Calculator!$B$7)) | I15: =IF($B15="","",$L14*Calculator!$B$6*$F15/Calculator!$B$7) | J15: =IF($B15="","",MAX(0,$H15-$I15)) | K15: =IF($B15="","",IF($D15<>"",$D15,$G15-$H15)) | L15: =IF($B15="","",$L14-$K15)
A16: 10 | F16: =IF($B16="","",$B16-$B15) | G16: =IF($B16="","",IF($C16<>"",$C16,N($D16)+N($E16))) | H16: =IF($B16="","",IF($E16<>"",$E16,$L15*Calculator!$B$5*$F16/Calculator!$B$7)) | I16: =IF($B16="","",$L15*Calculator!$B$6*$F16/Calculator!$B$7) | J16: =IF($B16="","",MAX(0,$H16-$I16)) | K16: =IF($B16="","",IF($D16<>"",$D16,$G16-$H16)) | L16: =IF($B16="","",$L15-$K16)
A17: 11 | F17: =IF($B17="","",$B17-$B16) | G17: =IF($B17="","",IF($C17<>"",$C17,N($D17)+N($E17))) | H17: =IF($B17="","",IF($E17<>"",$E17,$L16*Calculator!$B$5*$F17/Calculator!$B$7)) | I17: =IF($B17="","",$L16*Calculator!$B$6*$F17/Calculator!$B$7) | J17: =IF($B17="","",MAX(0,$H17-$I17)) | K17: =IF($B17="","",IF($D17<>"",$D17,$G17-$H17)) | L17: =IF($B17="","",$L16-$K17)
A18: 12 | F18: =IF($B18="","",$B18-$B17) | G18: =IF($B18="","",IF($C18<>"",$C18,N($D18)+N($E18))) | H18: =IF($B18="","",IF($E18<>"",$E18,$L17*Calculator!$B$5*$F18/Calculator!$B$7)) | I18: =IF($B18="","",$L17*Calculator!$B$6*$F18/Calculator!$B$7) | J18: =IF($B18="","",MAX(0,$H18-$I18)) | K18: =IF($B18="","",IF($D18<>"",$D18,$G18-$H18)) | L18: =IF($B18="","",$L17-$K18)
A19: 13 | F19: =IF($B19="","",$B19-$B18) | G19: =IF($B19="","",IF($C19<>"",$C19,N($D19)+N($E19))) | H19: =IF($B19="","",IF($E19<>"",$E19,$L18*Calculator!$B$5*$F19/Calculator!$B$7)) | I19: =IF($B19="","",$L18*Calculator!$B$6*$F19/Calculator!$B$7) | J19: =IF($B19="","",MAX(0,$H19-$I19)) | K19: =IF($B19="","",IF($D19<>"",$D19,$G19-$H19)) | L19: =IF($B19="","",$L18-$K19)
A20: 14 | F20: =IF($B20="","",$B20-$B19) | G20: =IF($B20="","",IF($C20<>"",$C20,N($D20)+N($E20))) | H20: =IF($B20="","",IF($E20<>"",$E20,$L19*Calculator!$B$5*$F20/Calculator!$B$7)) | I20: =IF($B20="","",$L19*Calculator!$B$6*$F20/Calculator!$B$7) | J20: =IF($B20="","",MAX(0,$H20-$I20)) | K20: =IF($B20="","",IF($D20<>"",$D20,$G20-$H20)) | L20: =IF($B20="","",$L19-$K20)
A21: 15 | F21: =IF($B21="","",$B21-$B20) | G21: =IF($B21="","",IF($C21<>"",$C21,N($D21)+N($E21))) | H21: =IF($B21="","",IF($E21<>"",$E21,$L20*Calculator!$B$5*$F21/Calculator!$B$7)) | I21: =IF($B21="","",$L20*Calculator!$B$6*$F21/Calculator!$B$7) | J21: =IF($B21="","",MAX(0,$H21-$I21)) | K21: =IF($B21="","",IF($D21<>"",$D21,$G21-$H21)) | L21: =IF($B21="","",$L20-$K21)
... A406: 400 | F406: =IF($B406="","",$B406-$B405) | G406: =IF($B406="","",IF($C406<>"",$C406,N($D406)+N($E406))) | H406: =IF($B406="","",IF($E406<>"",$E406,$L405*Calculator!$B$5*$F406/Calculator!$B$7)) | I406: =IF($B406="","",$L405*Calculator!$B$6*$F406/Calculator!$B$7) | J406: =IF($B406="","",MAX(0,$H406-$I406)) | K406: =IF($B406="","",IF($D406<>"",$D406,$G406-$H406)) | L406: =IF($B406="","",$L405-$K406)
